gsheetx/__init__.py
gsheetx/__main__.py
gsheetx/gsheetx.py
gsheetx/utils.py
gsheetx-0.0.9.dist-info/LICENSE
gsheetx-0.0.9.dist-info/METADATA
gsheetx-0.0.9.dist-info/WHEEL
gsheetx-0.0.9.dist-info/entry_points.txt
gsheetx-0.0.9.dist-info/top_level.txt
gsheetx-0.0.9.dist-info/RECORD
