Metadata-Version: 2.1
Name: gsheetx
Version: 0.0.9
Summary: CLI for Google Spreadsheet
Home-page: https://github.com/Minyus/g-sheet-x
Author: Yusuke Minami
Author-email: me@minyus.github.com
License: MIT
Keywords: Google,sheet,gspread
Classifier: Development Status :: 3 - Alpha
Classifier: Natural Language :: English
Classifier: Programming Language :: Python :: 3.8
Classifier: Programming Language :: Python :: 3.9
Classifier: Programming Language :: Python :: 3.10
Classifier: Programming Language :: Python :: 3.11
Classifier: Programming Language :: Python :: 3.12
Classifier: Programming Language :: Python :: 3.13
Classifier: Operating System :: OS Independent
License-File: LICENSE
Requires-Dist: fire
Requires-Dist: gspread
